image_processor_pkg/__init__.py
image_processor_pkg/image_filters/__init__.py
image_processor_pkg/image_filters/blur_filter.py
image_processor_pkg/image_filters/sharpen_filter.py
image_processor_pkg/image_transforms/__init__.py
image_processor_pkg/image_transforms/resize_transform.py
image_processor_pkg/image_transforms/rotate_transform.py
image_processor_pkg-0.0.1.dist-info/METADATA
image_processor_pkg-0.0.1.dist-info/WHEEL
image_processor_pkg-0.0.1.dist-info/top_level.txt
image_processor_pkg-0.0.1.dist-info/RECORD
